README.rst
setup.py
fbscraper/__init__.py
fbscraper/fbscraper.py
fbscraper.egg-info/PKG-INFO
fbscraper.egg-info/SOURCES.txt
fbscraper.egg-info/dependency_links.txt
fbscraper.egg-info/requires.txt
fbscraper.egg-info/top_level.txt