Metadata-Version: 1.1
Name: fbscraper
Version: 1.0
Summary: A cli script that scrapes images and videos from a Facebook profile
Home-page: UNKNOWN
Author: onyeabor
Author-email: onyeabor@riseup.net
License: MIT
Keywords: facebook scraper scraping
Platform: UNKNOWN
Classifier: Development Status :: 5 - Production/Stable
Classifier: Programming Language :: Python :: 3
Classifier: Programming Language :: Python :: 3.5
Classifier: Programming Language :: Python :: 3.6
Classifier: Programming Language :: Python :: Implementation :: CPython
Classifier: Topic :: Utilities
